brinjal/__init__.py
brinjal/_version.py
brinjal/manager.py
brinjal/models.py
brinjal/task.py
brinjal/api/router.py
brinjal/api/static/TaskList.js
brinjal/api/static/test.html
brinjal-0.8.0.dist-info/METADATA
brinjal-0.8.0.dist-info/WHEEL
brinjal-0.8.0.dist-info/licenses/LICENSE.txt
brinjal-0.8.0.dist-info/RECORD
