Metadata-Version: 2.4
Name: brinjal
Version: 0.8.0
Summary: A generic, reusable task management system built with FastAPI and asyncio
Project-URL: Homepage, https://github.com/sg-s/brinjal
Project-URL: Documentation, https://sg-s.github.io/brinjal
Project-URL: Repository, https://github.com/sg-s/brinjal
Project-URL: Issues, https://github.com/sg-s/brinjal/issues
Author-email: Srinivas Gorur-Shandilya <code@srinivas.gs>
License-File: LICENSE.txt
Keywords: asyncio,fastapi,progress-tracking,sse,task-management
Classifier: Development Status :: 4 - Beta
Classifier: Framework :: FastAPI
Classifier: Intended Audience :: Developers
Classifier: License :: OSI Approved :: MIT License
Classifier: Operating System :: OS Independent
Classifier: Programming Language :: Python :: 3
Classifier: Programming Language :: Python :: 3.13
Classifier: Topic :: Software Development :: Libraries :: Python Modules
Classifier: Topic :: System :: Distributed Computing
Requires-Python: >=3.12
Requires-Dist: beartype>=0.21.0
Requires-Dist: croniter>=2.0.0
Requires-Dist: fastapi>=0.116.1
Requires-Dist: pydantic>=2.11.7
Requires-Dist: uvicorn>=0.35.0
Provides-Extra: build
Requires-Dist: build>=1.0.0; extra == 'build'
Provides-Extra: docs
Requires-Dist: mkdocs-material>=9.0.0; extra == 'docs'
Requires-Dist: mkdocs>=1.5.0; extra == 'docs'
Requires-Dist: mkdocstrings[python]>=0.24.0; extra == 'docs'
